kallia-0.1.6.dist-info/licenses/LICENSE
kallia_core/__init__.py
kallia_core/chunker.py
kallia_core/constants.py
kallia_core/documents.py
kallia_core/exceptions.py
kallia_core/image_caption_serializer.py
kallia_core/logger.py
kallia_core/main.py
kallia_core/memories.py
kallia_core/messages.py
kallia_core/models.py
kallia_core/prompts.py
kallia_core/settings.py
kallia_core/unordered_list_serializer.py
kallia_core/utils.py
kallia-0.1.6.dist-info/METADATA
kallia-0.1.6.dist-info/WHEEL
kallia-0.1.6.dist-info/top_level.txt
kallia-0.1.6.dist-info/RECORD
