Metadata-Version: 2.4
Name: kallia
Version: 0.1.6
Summary: Semantic Document Processing Library
Author-email: CK <ck@kallia.net>
License-Expression: Apache-2.0
Project-URL: Homepage, https://github.com/kallia-project/kallia
Project-URL: Issues, https://github.com/kallia-project/kallia/issues
Keywords: document-processing,semantic-chunking,document-analysis,text-processing,machine-learning
Classifier: Operating System :: OS Independent
Classifier: Development Status :: 5 - Production/Stable
Classifier: Intended Audience :: Developers
Classifier: Intended Audience :: Science/Research
Classifier: Topic :: Scientific/Engineering :: Artificial Intelligence
Classifier: Programming Language :: Python :: 3
Classifier: Programming Language :: Python :: 3.9
Classifier: Programming Language :: Python :: 3.10
Classifier: Programming Language :: Python :: 3.11
Classifier: Programming Language :: Python :: 3.12
Classifier: Programming Language :: Python :: 3.13
Requires-Python: >=3.11
License-File: LICENSE
Requires-Dist: fastapi[standard]==0.115.14
Requires-Dist: docling==2.41.0
Dynamic: license-file
